LICENSE
README.md
setup.py
emerald_shapeutils/__init__.py
emerald_shapeutils/alignment.py
emerald_shapeutils.egg-info/PKG-INFO
emerald_shapeutils.egg-info/SOURCES.txt
emerald_shapeutils.egg-info/dependency_links.txt
emerald_shapeutils.egg-info/requires.txt
emerald_shapeutils.egg-info/top_level.txt