Metadata-Version: 2.1
Name: emerald-shapeutils
Version: 0.0.3
Summary: Utils for handling shapes and rasters
Home-page: https://github.com/emerald-geomodelling/emerald-shapeutils
Author: Craig William Christensen, Egil Moeller and others 
Author-email: cch@emrld.no, em@emrld.no
License-File: LICENSE
